dl_a2t-0.0.2.4.dist-info/METADATA
dl_a2t-0.0.2.4.dist-info/WHEEL
dl_a2t-0.0.2.4.dist-info/entry_points.txt
dl_a2t/cli.py
dl_a2t/impl/download.py
dl_a2t/impl/transcript.py
dl_a2t/utils/cache.py
dl_a2t/utils/constants.py
dl_a2t/utils/model.py
dl_a2t-0.0.2.4.dist-info/RECORD
