Metadata-Version: 2.1
Name: dl-a2t
Version: 0.0.2.4
Summary: Download audio from YouTube and transcribe it
Requires-Python: >=3.12
Requires-Dist: diskcache2<1.1.0,>=0.1.1
Requires-Dist: openai-whisper>=20240930
Requires-Dist: rich<14.1.0,>=13.9.4
Requires-Dist: typer-slim~=0.15.0
Requires-Dist: yt-dlp[default]<2025.4.0,>=2024.11.4
